culebra/__init__.py
culebra-0.0.2.dist-info/METADATA
culebra-0.0.2.dist-info/WHEEL
culebra-0.0.2.dist-info/top_level.txt
culebra-0.0.2.dist-info/RECORD
