Metadata-Version: 2.1
Name: culebra
Version: 0.0.2
Summary: Web Framework 
Home-page: https://github.com/xerxes23/culebra
Author: Joseph Mendoza
Author-email: UNKNOWN
License: MIT
Platform: UNKNOWN
